setup_client.py
client/__init__.py
client/client.py
client/decos.py
client/descriptors.py
client/errors.py
client/metaclass.py
client/client/__init__.py
client/client/add_contact.py
client/client/database.py
client/client/delete_contact.py
client/client/main_window.py
client/client/main_window_conv.py
client/client/start_dialog.py
client/client/transport.py
client/common/__init__.py
client/common/utils.py
client/common/variables.py
client/configs/__init__.py
client/configs/config_client_log.py
client/configs/config_server_log.py
client/doc/__init__.py
client/doc/source/__init__.py
client/doc/source/conf.py
mess_client_fatfar.egg-info/PKG-INFO
mess_client_fatfar.egg-info/SOURCES.txt
mess_client_fatfar.egg-info/dependency_links.txt
mess_client_fatfar.egg-info/requires.txt
mess_client_fatfar.egg-info/top_level.txt