Metadata-Version: 1.0
Name: mess-client-fatfar
Version: 0.0.1
Summary: mess_client
Home-page: UNKNOWN
Author: Farid Fatekhov
Author-email: fatar@yandex.ru
License: UNKNOWN
Platform: UNKNOWN
